FPGA/Verilog/beginner/2/adder4.v
module adder4(
    input [3:0] a, b,

    output [3:0] sum,
    output wire carry_out
);

    wire c0, c1, c2;

    assign c0 = a[0] & b[0];
    assign sum[0] = a[0] ^ b[0];

    assign c1 = (a[1] & b[1])| (b[1] & c0 ) | (a[1] & c0 );
    assign sum[1] = a[1] ^ b[1] ^ c0;
    
    assign c2 = (a[2] & b[2])| (b[2] & c1) | (a[2] & c1); 
    assign sum[2] = a[2] ^ b[2] ^ c1;

    assign carry_out  = (a[3] & b[3])| (b[3] & c2 ) | (a[3] & c0 );
    assign sum[3] = a[3] ^ b[3] ^ c2;


endmodule

FPGA/Verilog/beginner/2/adder4_tb.v
`timescale 1ns/1ps

module adder4_tb;

    reg [3:0]a, b;

    wire [3:0] sum;
    wire carry_out;


    adder4 dut(
        .a(a),
        .b(b),
        .sum(sum),
        .carry_out(carry_out)
    );


    initial begin 
        $dumpfile("wave.vcd");  
            $dumpvars(0, adder4_tb);

            a = 0; b = 0; #10;
            $display("%b + %b = %b%b", a, b, carry_out,sum);

            a = 1; b = 0; #10;
            $display("%b + %b = %b%b", a, b, carry_out,sum);

            a = 0; b = 1; #10;
            $display("%b + %b = %b%b", a, b, carry_out,sum);

            a = 1; b = 1; #10;
            $display("%b + %b = %b%b", a, b, carry_out,sum);

            a = 2; b = 0; #10;
            $display("%b + %b = %b%b", a, b, carry_out,sum);

            a = 4; b = 0; #10;
            $display("%b + %b = %b%b", a, b, carry_out,sum);

            a = 2; b = 4; #10;
            $display("%b + %b = %b%b", a, b, carry_out, sum);

            a = 8; b = 8; #10;
            $display("%b + %b = %b%b", a, b, carry_out, sum);

        $finish;

    end 

endmodule

FPGA/Verilog/beginner/2/wave.vcd
$date
	Wed Oct 15 03:47:46 2025
$end
$version
	Icarus Verilog
$end
$timescale
	1ps
$end
$scope module adder4_tb $end
$var wire 4 ! sum [3:0] $end
$var wire 1 " carry_out $end
$var reg 4 # a [3:0] $end
$var reg 4 $ b [3:0] $end
$scope module dut $end
$var wire 4 % a [3:0] $end
$var wire 4 & b [3:0] $end
$var wire 1 ' c0 $end
$var wire 1 ( c1 $end
$var wire 1 ) c2 $end
$var wire 1 " carry_out $end
$var wire 4 * sum [3:0] $end
$upscope $end
$upscope $end
$enddefinitions $end
$comment Show the parameter values. $end
$dumpall
$end
#0
$dumpvars
b0 *
0)
0(
0'
b0 &
b0 %
b0 $
b0 #
0"
b0 !
$end
#10000
b1 !
b1 *
b1 #
b1 %
#20000
b1 $
b1 &
b0 #
b0 %
#30000
1'
b10 !
b10 *
b1 #
b1 %
#40000
b10 !
b10 *
0(
0'
b0 $
b0 &
b10 #
b10 %
#50000
b100 !
b100 *
b100 #
b100 %
#60000
b110 !
b110 *
b100 $
b100 &
b10 #
b10 %
#70000
1"
b0 !
b0 *
b1000 $
b1000 &
b1000 #
b1000 %
